CHANGES.txt
COPYING
MANIFEST.in
README.txt
setup.py
yaco/__init__.py
yaco.recipe.cert.egg-info/PKG-INFO
yaco.recipe.cert.egg-info/SOURCES.txt
yaco.recipe.cert.egg-info/dependency_links.txt
yaco.recipe.cert.egg-info/entry_points.txt
yaco.recipe.cert.egg-info/namespace_packages.txt
yaco.recipe.cert.egg-info/not-zip-safe
yaco.recipe.cert.egg-info/requires.txt
yaco.recipe.cert.egg-info/top_level.txt
yaco/recipe/__init__.py
yaco/recipe/cert/__init__.py