Metadata-Version: 1.0
Name: yaco.recipe.cert
Version: 0.1.1
Summary: Buildout recipe for creating self signed certificates
Home-page: http://bitbucket.org/lgs/yaco.recipe.cert
Author: Yaco Sistemas (Lorenzo Gil)
Author-email: lgs@yaco.es
License: LGPL
Keywords: buildout certificate
Platform: UNKNOWN
Classifier: Development Status :: 4 - Beta
Classifier: Framework :: Buildout
Classifier: Framework :: Buildout :: Recipe
